Simple_Notification_Lambda/__init__.py
Simple_Notification_Lambda/notifier.py
Simple_Notification_Lambda-0.1.1.dist-info/LICENSE
Simple_Notification_Lambda-0.1.1.dist-info/METADATA
Simple_Notification_Lambda-0.1.1.dist-info/WHEEL
Simple_Notification_Lambda-0.1.1.dist-info/top_level.txt
Simple_Notification_Lambda-0.1.1.dist-info/RECORD
