Metadata-Version: 2.1
Name: Simple_Notification_Lambda
Version: 0.1.1
Summary: A package to send Slack notifications via AWS Lambda
Author: Vikas
Author-email: vikasingawale16@gmail.com
Classifier: Programming Language :: Python :: 3
Classifier: License :: OSI Approved :: MIT License
Classifier: Operating System :: OS Independent
Requires-Python: >=3.6
License-File: LICENSE
Requires-Dist: boto3>=1.26.0
